schedule_manager_ui/__init__.py
schedule_manager_ui/manager.py
schedule_manager_ui/templates/index.html
schedule_manager_ui/templates/logs.html
schedule_manager_ui/templates/script.js
schedule_manager_ui/templates/styles.css
schedule_manager_ui-0.0.7.dist-info/LICENSE
schedule_manager_ui-0.0.7.dist-info/METADATA
schedule_manager_ui-0.0.7.dist-info/WHEEL
schedule_manager_ui-0.0.7.dist-info/top_level.txt
schedule_manager_ui-0.0.7.dist-info/RECORD
