Metadata-Version: 2.1
Name: schedule-manager-ui
Version: 0.0.7
Summary: Web UI for seamless interaction with APScheduler job schedulers, ready to use out of the box. Execution logs history is availble.
Author-email: macinn <marcinsk1122@gmail.com>
License: Copyright (c) 2018 The Python Packaging Authority
Project-URL: Home, https://github.com/macinn/schedule-manager-ui
Project-URL: Repository, https://github.com/macinn/schedule-manager-ui
Project-URL: Issues, https://github.com/macinn/schedule-manager-ui/issues
Keywords: python,flask,apscheduler,jobs,manager,ui,web
Classifier: Framework :: Flask
Classifier: Programming Language :: Python :: 3
Classifier: Operating System :: OS Independent
Requires-Python: >=3.8
License-File: LICENSE
Requires-Dist: flask
Requires-Dist: apscheduler
Requires-Dist: sqlalchemy
Requires-Dist: pytz
